recombinant/__init__.py
recombinant-1.1.0.dist-info/LICENSE
recombinant-1.1.0.dist-info/METADATA
recombinant-1.1.0.dist-info/WHEEL
recombinant-1.1.0.dist-info/top_level.txt
recombinant-1.1.0.dist-info/RECORD
