Metadata-Version: 2.1
Name: recombinant
Version: 1.1.0
Summary: Phonotactic generalization using recombination
Author-email: Ignas Rudaitis <ignas.rudaitis@gmail.com>
License: MIT License        
Keywords: linguistics,phonotactics
Classifier: License :: OSI Approved :: MIT License
Classifier: Programming Language :: Python
Classifier: Programming Language :: Python :: 3
Requires-Python: >=3.7
License-File: LICENSE
Requires-Dist: tqdm
Requires-Dist: sortedcontainers
